setup.py
gaussdistbiodist/Binomialdistribution.py
gaussdistbiodist/Gaussiandistribution.py
gaussdistbiodist/Generaldistribution.py
gaussdistbiodist/__init__.py
gaussdistbiodist.egg-info/PKG-INFO
gaussdistbiodist.egg-info/SOURCES.txt
gaussdistbiodist.egg-info/dependency_links.txt
gaussdistbiodist.egg-info/not-zip-safe
gaussdistbiodist.egg-info/top_level.txt