Metadata-Version: 1.0
Name: gaussdistbiodist
Version: 1.0
Summary: Gaussian and Binomial distributions
Home-page: UNKNOWN
Author: Shrenik Doshi
Author-email: doshishrenik0120@gmail.com
License: UNKNOWN
Platform: UNKNOWN
